textknnassifier/__init__.py
textknnassifier/classifier.py
textknnassifier/compressor.py
textknnassifier-0.0.1.dist-info/LICENSE
textknnassifier-0.0.1.dist-info/METADATA
textknnassifier-0.0.1.dist-info/WHEEL
textknnassifier-0.0.1.dist-info/RECORD
