Metadata-Version: 2.1
Name: textknnassifier
Version: 0.0.1
Summary: TextKNNClassifier is a k-nearest neighbors classifier for text data. It uses a compression algorithm to compute the distance between texts and predicts the label of a test entry based on the labels of the k-nearest neighbors in the training data.
License: LGPL-2.1
Author: Reinder Vos de Wael
Author-email: reinder.vosdewael@childmind.org
Requires-Python: >=3.8,<4.0
Classifier: License :: OSI Approved
Classifier: Programming Language :: Python :: 3
Classifier: Programming Language :: Python :: 3.8
Classifier: Programming Language :: Python :: 3.9
Classifier: Programming Language :: Python :: 3.10
Classifier: Programming Language :: Python :: 3.11
Provides-Extra: docs
